Workbook

Sheet Sheet1
B2: OOO "SAMPLE"
B3: Критерий | D3: Показатель | E3: Результат | G3: А
B4: KATM | D4: 400 | E4: =IF(ISNA(D4),0, IF(D4>=401,100, IF(D4>=301,80, IF(D4>=201,60, IF(D4>=101,20, IF(D4>=0,0,0)))))) -> 80 | F4: MAX 100
B5: Сумма кредита | D5: 1000000000 | E5: =IF(ISNA(D5),0, IF(D5>=100000000000,0, IF(D5>=10000000000,50, IF(D5>=5000000000,70, IF(D5>=1,100,0))))) -> 100 | F5: MAX 100
B6: LGD | D6: =LGD!G7 -> 10 | E6: =IF(ISNA(LGD!G7),0, IF(LGD!G7=10,100, IF(LGD!G7>=8,60, IF(LGD!G7>=6,40, IF(LGD!G7>=4,10, IF(LGD!G7>=0,0,0)))))) -> 100 | F6: MAX 100
B7: Оборот среднемесячный | D7: =Оборотка!I21 -> 1.8855745e+09 | E7: =IF(ISNA(D7),0, IF(D7>=5000000000,100, IF(D7>=4000000000,60, IF(D7>=3000000000,40, IF(D7>=2000000000,20, IF(D7>=0,0,0)))))) -> 0 | F7: MAX 100
B8: Долговая нагрузка | D8: =Оборотка!I26 -> 0 | E8: =IF(ISNA(D8),0, IF(D8>=2,10, IF(D8>=1,20, IF(D8>=0.5,50, IF(D8>=0.3,80, IF(D8>=0.1,90, IF(D8>=0,100,0))))))) -> 100 | F8: MAX 100
B9: Ликвидность (текущая) | D9: =(Баланс!D6+Баланс!D7)/Баланс!D10 -> 2.4535124 | E9: =IF(ISNA(D9),0, IF(D9>=2,70, IF(D9>=0.8,100, IF(D9>=0.5,40, IF(D9>=0.4,30, IF(D9>=0,0,0)))))) -> 70 | F9: MAX 100 | G9: =+SUM(E4:E13) -> 850
B10: Автономия | D10: =(Баланс!D8-Баланс!D9)/(Баланс!D11-Баланс!D4) -> 0.87492562 | E10: =IF(OR(ISNA(D10),D10="", NOT(ISNUMBER(D10))),0, IF(D10<0.5,0,100)) -> 100 | F10: MAX 100
B11: Покрытия | D11: =(Баланс!D4+Баланс!D6+Баланс!D7)/Баланс!D10 -> 2.4535124 | E11: =IF(ISNA(D11),0, IF(D11>=3,1, IF(D11>=1.5,100, IF(D11>=1,60, IF(D11>=0.5,10, IF(D11>=0,0,0)))))) -> 100 | F11: MAX 100
B12: Chamber.uz | D12: 86 | E12: =IF(ISNA(D12),0, IF(D12>=86,100, IF(D12>=56,70, IF(D12>=26,50, IF(D12>=0,0,0))))) -> 100 | F12: MAX 100
B13: Дата открытия пп | D13: 1990 | E13: =IF(ISNA(D13),0, IF(YEAR(TODAY())-D13>=5,100, IF(YEAR(TODAY())-D13>=4,80, IF(YEAR(TODAY())-D13>=3,60, IF(YEAR(TODAY())-D13>=2,40, IF(YEAR(TODAY())-D13>=1,20,0)))))) -> 100 | F13: MAX 100

Sheet Баланс
B2: Показатели баланса Ф1, Ф2
B3: Наименование показателя | C3: Код стр. | D3: Показатель на отчетную дату
B4: Остаточная (балансовая) стоимость (стр. 020-021) | C4: Ф1: 022 | D4: 0
B5: Товарно-материальные запасы, всего (стр. 150 + 160 + 170 + 180) | C5: Ф1: 140 | D5: 2358000.9
B6: Дебиторы, всего (стр. 220 + 230 + 240 + 250 + 260 + 270 + 280 + 290 + 300 + 310) | C6: Ф1: 210 | D6: 0
B7: Денежные средства, всего (стр. 330+340+350+360) | C7: Ф1: 320 | D7: 76000
B8: Источники собственных средств (стр. 410+420+430-440+450+460+470) | C8: Ф1: 480 | D8: 4920582.5
B9: Долгоср. задолж. обособленным подразделениям (7110) | C9: Ф1: 510 | D9: 0
B10: Текущие обязательства, всего (стр. 610 + 620 + 630 + … + 740 + 750 + 760) | C10: Ф1: 600 | D10: 30976
B11: ВСЕГО ПО ПАССИВУ БАЛАНСА (стр. 480+стр. 770) | C11: Ф1: 780 | D11: 5624000.9

Sheet Оборотка
B1: Информация об оборотах компани по расчётным счетам (наличие других счетов сверить с НИББД)
B2: Оборотка клиента
B3: Обслуживающий банк | C3: Уникал | D3: Период (начало-конец) | F3: Валюта счёта | G3: Дебет | H3: Кредит | I3: Среднемесячный оборот по счёту
B4: ТБС | C4: 00547227 | D4: 45435 | E4: 45799 | F4: UZS | G4: 1905046700 | H4: 1.9065253e+09 | I4: =IFERROR(H4/((E4-D4)/30),0) -> 1.5713121e+08
B5: ТБС | C5: 00547227 | D5: 45435 | E5: 45799 | F5: UZS | G5: 1905046700 | H5: 1.9065253e+09 | I5: =IFERROR(H5/((E5-D5)/30),0) -> 1.5713121e+08
B6: ТБС | C6: 00547227 | D6: 45435 | E6: 45799 | F6: UZS | G6: 1905046700 | H6: 1.9065253e+09 | I6: =IFERROR(H6/((E6-D6)/30),0) -> 1.5713121e+08
B7: ТБС | C7: 00547227 | D7: 45435 | E7: 45799 | F7: UZS | G7: 1905046700 | H7: 1.9065253e+09 | I7: =IFERROR(H7/((E7-D7)/30),0) -> 1.5713121e+08
B8: ТБС | C8: 00547227 | D8: 45435 | E8: 45799 | F8: UZS | G8: 1905046700 | H8: 1.9065253e+09 | I8: =IFERROR(H8/((E8-D8)/30),0) -> 1.5713121e+08
B9: ТБС | C9: 00547227 | D9: 45435 | E9: 45799 | F9: UZS | G9: 1905046700 | H9: 1.9065253e+09 | I9: =IFERROR(H9/((E9-D9)/30),0) -> 1.5713121e+08
B10: ТБС | C10: 00547227 | D10: 45435 | E10: 45799 | F10: UZS | G10: 1905046700 | H10: 1.9065253e+09 | I10: =IFERROR(H10/((E10-D10)/30),0) -> 1.5713121e+08
B11: ТБС | C11: 00547228 | D11: 45436 | E11: 45800 | F11: UZS | G11: 1905046700 | H11: 1.9065253e+09 | I11: =IFERROR(H11/((E11-D11)/30),0) -> 1.5713121e+08
B12: ТБС | C12: 00547229 | D12: 45437 | E12: 45801 | F12: UZS | G12: 1905046700 | H12: 1.9065253e+09 | I12: =IFERROR(H12/((E12-D12)/30),0) -> 1.5713121e+08
B13: ТБС | C13: 00547230 | D13: 45438 | E13: 45802 | F13: UZS | G13: 1905046700 | H13: 1.9065253e+09 | I13: =IFERROR(H13/((E13-D13)/30),0) -> 1.5713121e+08
B14: ТБС | C14: 00547231 | D14: 45439 | E14: 45803 | F14: UZS | G14: 1905046700 | H14: 1.9065253e+09 | I14: =IFERROR(H14/((E14-D14)/30),0) -> 1.5713121e+08
B15: ТБС | C15: 00547227 | D15: 45435 | E15: 45799 | F15: UZS | G15: 1905046700 | H15: 1.9065253e+09 | I15: =IFERROR(H15/((E15-D15)/30),0) -> 1.5713121e+08
B17: ИТОГО UZS | F17: UZS | G17: =SUMIF(F4:F16,F17,G4:G16) -> 22860560400 | H17: =SUMIF(F4:F16,F17,H4:H16) -> 2.2878304e+10 | I17: =SUM(I4:I15) -> 1.8855745e+09
B18: ИТОГО USD | F18: USD | G18: =SUMIF(F4:F16,F18,G4:G16) -> 0 | H18: =SUMIF(F4:F16,F18,H4:H16) -> 0 | I18: =SUMIF(F4:F16,F18,I4:I16) -> 0
B19: ИТОГО EUR | F19: EUR | G19: =SUMIF(F4:F16,F19,G4:G16) -> 0 | H19: =SUMIF(F4:F16,F19,H4:H16) -> 0 | I19: =SUMIF(F4:F16,F19,I4:I16) -> 0
B20: ИТОГО РУБЛЬ | F20: РУБЛЬ | G20: =SUMIF(F4:F16,F20,G4:G16) -> 0 | H20: =SUMIF(F4:F16,F20,H4:H16) -> 0 | I20: =SUMIF(F4:F16,F20,I4:I16) -> 0
B21: ИТОГО UZS | F21: UZS | G21: =G17+(G18*C24)+(G19*C25)+(G20*C26) -> 22860560400 | H21: =H17+(H18*C24)+(H19*C25)+(H20*C26) -> 2.2878304e+10 | I21: =I17+(I18*C24)+(I19*C25)+(I20*C26) -> 1.8855745e+09
B23: Курс валют | F23: Кредитная нагрузка относительно оборотов
B24: $ Курс ДОЛЛАРА | C24: 13000 | D24: сум | F24: Соха | G24: O’rtacha 1 oylik debet aylnama | H24: O’rtacha 1 oylik qarz yuki | I24: Nisbati
B25: € Курс ЕВРО | C25: 14000 | D25: сум
B26: ₽ Курс РУБЛЯ | C26: 120 | D26: сум | F26: Корпоратив | G26: =I21 -> 1.8855745e+09 | I26: =H26/G26 -> 0

Sheet LGD
B2: № | C2: Тип залога: | D2: Уровень ликвидности | E2: Уд. вес | F2: Залоговый вес * | G2: Балл
B3: 1 | C3: Гос гарантии, депозиты, ценные бумаги, драгметаллы | D3: Очень высокий | E3: 10 | F3: 1 | G3: =E3*F3 -> 10
B4: 2 | C4: Недвижимость | D4: Высокий | E4: 8 | G4: =E4*F4 -> 0
B5: 3 | C5: Авто, Техники, спецтехники | D5: Средний | E5: 6 | G5: =E5*F5 -> 0
B6: 4 | C6: Страховые полисы | D6: Низкий | E6: 2 | G6: =E6*F6 -> 0
F7: =SUM(F3:F6) -> 1 | G7: =SUM(G3:G6) -> 10
F8: * не должно превышать 100% | G8: максимум 10

Sheet Лист1
B2: Mulk turi | C2: мол-мулк гарови | F2: тадбиркорлик ривож комп, 3 шахс | I2: суғурта
C3: улуши | D3: БАЛЛ | E3: Тўпланган балл | F3: улуши | G3: БАЛЛ | H3: Тўпланган балл | I3: улуши | J3: БАЛЛ | K3: Тўпланган балл | L3: 1,3--21% | M3: 1,3--20% | N3: 1,3--10% | O3: 1,3--1% | P3: 2--21% | Q3: 2--20% | R3: 2--10% | S3: 2--1% | T3: 3--21% | U3: 3--20% | V3: 3--10% | W3: 3--1%
B4: Ko'chmas mulk | C4: 100 | D4: 50 | E4: =C4*D4/100 -> 50 | F4: 100 | G4: 40 | H4: =F4*G4/100 -> 40 | I4: 100 | J4: 35 | K4: =I4*J4/100 -> 35 | L4: =G4*79%+21%*$G$10 -> 34.75 | M4: =G4*80%+20%*$G$10 -> 35 | N4: =G4*90%+10%*$G$10 -> 37.5 | O4: =G4*99%+$G$10*1% -> 39.75 | P4: =J4*79%+21%*$J$11 -> 32.9 | Q4: =J4*80%+20%*$J$11 -> 33 | R4: =J4*90%+10%*$J$11 -> 34 | S4: =J4*99%+$J$11*1% -> 34.9 | T4: =G4*79%+21%*$G$12 -> 34.75 | U4: =G4*80%+20%*$G$12 -> 35 | V4: =G4*90%+10%*$G$12 -> 37.5 | W4: =G4*99%+$G$12*1% -> 39.75
B5: Yengil avtotransport vositalari | C5: 100 | D5: 45 | E5: =C5*D5/100 -> 45 | F5: 100 | G5: 30 | H5: =F5*G5/100 -> 30 | I5: 100 | J5: 30 | K5: =I5*J5/100 -> 30 | L5: =G5*79%+21%*$G$10 -> 26.85 | M5: =G5*80%+20%*$G$10 -> 27 | N5: =G5*90%+10%*$G$10 -> 28.5 | O5: =G5*99%+$G$10*1% -> 29.85 | P5: =J5*79%+21%*$J$11 -> 28.95 | Q5: =J5*80%+20%*$J$11 -> 29 | R5: =J5*90%+10%*$J$11 -> 29.5 | S5: =J5*99%+$J$11*1% -> 29.95 | T5: =G5*79%+21%*$G$12 -> 26.85 | U5: =G5*80%+20%*$G$12 -> 27 | V5: =G5*90%+10%*$G$12 -> 28.5 | W5: =G5*99%+$G$12*1% -> 29.85
B6: Depozit, oltindan yasalgan zargarlik buyumlari | C6: 100 | D6: 50 | E6: =C6*D6/100 -> 50 | F6: 100 | G6: 35 | H6: =F6*G6/100 -> 35 | I6: 100 | J6: 35 | K6: =I6*J6/100 -> 35 | L6: =G6*79%+21%*$G$10 -> 30.8 | M6: =G6*80%+20%*$G$10 -> 31 | N6: =G6*90%+10%*$G$10 -> 33 | O6: =G6*99%+$G$10*1% -> 34.8 | P6: =J6*79%+21%*$J$11 -> 32.9 | Q6: =J6*80%+20%*$J$11 -> 33 | R6: =J6*90%+10%*$J$11 -> 34 | S6: =J6*99%+$J$11*1% -> 34.9 | T6: =G6*79%+21%*$G$12 -> 30.8 | U6: =G6*80%+20%*$G$12 -> 31 | V6: =G6*90%+10%*$G$12 -> 33 | W6: =G6*99%+$G$12*1% -> 34.8
B7: Yuk transport vositalari | C7: 100 | D7: 35 | E7: =C7*D7/100 -> 35 | F7: 100 | G7: 30 | H7: =F7*G7/100 -> 30 | I7: 100 | J7: 30 | K7: =I7*J7/100 -> 30 | L7: =G7*79%+21%*$G$10 -> 26.85 | M7: =G7*80%+20%*$G$10 -> 27 | N7: =G7*90%+10%*$G$10 -> 28.5 | O7: =G7*99%+$G$10*1% -> 29.85 | P7: =J7*79%+21%*$J$11 -> 28.95 | Q7: =J7*80%+20%*$J$11 -> 29 | R7: =J7*90%+10%*$J$11 -> 29.5 | S7: =J7*99%+$J$11*1% -> 29.95 | T7: =G7*79%+21%*$G$12 -> 26.85 | U7: =G7*80%+20%*$G$12 -> 27 | V7: =G7*90%+10%*$G$12 -> 28.5 | W7: =G7*99%+$G$12*1% -> 29.85
B8: Maxsus texnika, avtobus va mikroavtobuslar | C8: 100 | D8: 35 | E8: =C8*D8/100 -> 35 | F8: 100 | G8: 30 | H8: =F8*G8/100 -> 30 | I8: 100 | J8: 30 | K8: =I8*J8/100 -> 30 | L8: =G8*79%+21%*$G$10 -> 26.85 | M8: =G8*80%+20%*$G$10 -> 27 | N8: =G8*90%+10%*$G$10 -> 28.5 | O8: =G8*99%+$G$10*1% -> 29.85 | P8: =J8*79%+21%*$J$11 -> 28.95 | Q8: =J8*80%+20%*$J$11 -> 29 | R8: =J8*90%+10%*$J$11 -> 29.5 | S8: =J8*99%+$J$11*1% -> 29.95 | T8: =G8*79%+21%*$G$12 -> 26.85 | U8: =G8*80%+20%*$G$12 -> 27 | V8: =G8*90%+10%*$G$12 -> 28.5 | W8: =G8*99%+$G$12*1% -> 29.85
B9: Uskunalar | C9: 100 | D9: 30 | E9: =C9*D9/100 -> 30 | F9: 100 | G9: 25 | H9: =F9*G9/100 -> 25 | I9: 100 | J9: 25 | K9: =I9*J9/100 -> 25 | L9: =G9*79%+21%*$G$10 -> 22.9 | M9: =G9*80%+20%*$G$10 -> 23 | N9: =G9*90%+10%*$G$10 -> 24 | O9: =G9*99%+$G$10*1% -> 24.9 | P9: =J9*79%+21%*$J$11 -> 25 | Q9: =J9*80%+20%*$J$11 -> 25 | R9: =J9*90%+10%*$J$11 -> 25 | S9: =J9*99%+$J$11*1% -> 25 | T9: =G9*79%+21%*$G$12 -> 22.9 | U9: =G9*80%+20%*$G$12 -> 23 | V9: =G9*90%+10%*$G$12 -> 24 | W9: =G9*99%+$G$12*1% -> 24.9
A10: 1 | B10: “Tadbirkorlikni rivojlantirish kompaniyasi” AJ kafilligi | C10: 100 | F10: 100 | G10: 15 | H10: =F10*G10/100 -> 15 | I10: 100 | J10: 15 | K10: =I10*J10/100 -> 15
A11: 2 | B11: Kredit qaytmaslik xatari boʻyicha sugʻurta polisi | C11: 100 | F11: 100 | I11: 100 | J11: 25 | K11: =I11*J11/100 -> 25
A12: 3 | B12: Uchinchi shaxs kafilligi | C12: 100 | F12: 100 | G12: 15 | H12: =F12*G12/100 -> 15 | I12: 100 | J12: 15 | K12: =I12*J12/100 -> 15
